{
  "home_team": "Canada",
  "away_team": "Bosnia and Herzegovina",
  "match_date": "2026-06-12",
  "group": "B",
  "venue": "BMO Field, Toronto, Canada",
  "h2h_summary": null,
  "h2h_record": null,
  "wc_history_home": null,
  "wc_history_away": null,
  "group_context": null,
  "strengths_home": null,
  "strengths_away": null,
  "team_style_home": null,
  "team_style_away": null,
  "injuries_home": [
    "Marcelo Flores (ACL)",
    "Moise Bombito (tibia)"
  ],
  "injuries_away": [],
  "odds": {
    "home_win": null,
    "draw": null,
    "away_win": null
  },
  "recent_news": "Canada coach Jesse Marsch is dealing with an injury problem ahead of their World Cup opener against Bosnia and Herzegovina. Canada seeks to begin the 2026 World Cup in style when facing Bosnia & Herzegovina in its opening Group B fixture.",
  "form_home": [],
  "form_away": [],
  "key_players_home": [
    "Liam Millar"
  ],
  "key_players_away": [],
  "context": null,
  "research_quality": "degraded"
}